aware_file_system/__init__.py
aware_file_system/config.py
aware_file_system/models.py
aware_file_system/operations.py
aware_file_system/change_tracking/__init__.py
aware_file_system/change_tracking/detector.py
aware_file_system/change_tracking/diff_calculator.py
aware_file_system/change_tracking/manager.py
aware_file_system/configs/__init__.py
aware_file_system/configs/default.yaml
aware_file_system/coordination/__init__.py
aware_file_system/coordination/coordinator.py
aware_file_system/coordination/events.py
aware_file_system/filters/__init__.py
aware_file_system/filters/base.py
aware_file_system/filters/composite.py
aware_file_system/filters/default.py
aware_file_system/filters/gitignore.py
aware_file_system/filters/regex.py
aware_file_system/index/__init__.py
aware_file_system/index/cache_models.py
aware_file_system/index/directory_cache.py
aware_file_system/index/file_metadata_cached.py
aware_file_system/index/file_system_index.py
aware_file_system/index/incremental_scanner.py
aware_file_system/index/index_storage.py
aware_file_system/introspection/__init__.py
aware_file_system/introspection/analyzer.py
aware_file_system/introspection/introspector.py
aware_file_system/introspection/singleton_introspector.py
aware_file_system/scripts/__init__.py
aware_file_system/scripts/copy_files.py
aware_file_system/scripts/introspect_project.py
aware_file_system/scripts/track_changes.py
aware_file_system/utils/__init__.py
aware_file_system/utils/script.py
aware_file_system/watcher/__init__.py
aware_file_system/watcher/file_system_watcher.py
aware_file_system-0.1.1.dist-info/METADATA
aware_file_system-0.1.1.dist-info/WHEEL
aware_file_system-0.1.1.dist-info/licenses/LICENSE
aware_file_system-0.1.1.dist-info/RECORD
