Metadata-Version: 2.4
Name: aware-file-system
Version: 0.1.1
Summary: Filesystem watcher and indexing utilities for aware-cli aware_sdk workflows.
Project-URL: Homepage, https://pypi.org/project/aware-file-system/
Project-URL: Source, https://github.com/aware-network/aware-sdk
Project-URL: Documentation, https://github.com/aware-network/aware-sdk/tree/main/libs/file_system/README.md
Project-URL: Changelog, https://github.com/aware-network/aware-sdk/tree/main/libs/file_system/CHANGELOG.md
Project-URL: Issues, https://github.com/aware-network/aware-sdk/issues
Author: AWARE Team
License: MIT License
License-File: LICENSE
Keywords: automation,aware,filesystem,watcher
Classifier: Intended Audience :: Developers
Classifier: License :: OSI Approved :: MIT License
Classifier: Operating System :: OS Independent
Classifier: Programming Language :: Python :: 3
Classifier: Programming Language :: Python :: 3.12
Classifier: Topic :: System :: Filesystems
Requires-Python: >=3.12
Requires-Dist: msgpack<2.0.0,>=1.1.1
Requires-Dist: pydantic<3.0.0,>=2.8.2
Requires-Dist: pyyaml<7.0.0,>=6.0.2
Provides-Extra: test
Requires-Dist: pytest-asyncio>=0.23.7; extra == 'test'
Requires-Dist: pytest>=8.4.2; extra == 'test'
